Metadata-Version: 2.1
Name: pug-watcher
Version: 1.0.5
Summary: Simple command-line Pug watcher/compiler made in Python
Home-page: https://github.com/AlexFlipnote/pug_watcher.py
Author: AlexFlipnote
License: UNKNOWN
Platform: UNKNOWN
License-File: LICENSE
